PrintTags/__init__.py
PrintTags/colors.py
PrintTags/print_tags.py
PrintTags/py.typed
tests/__init__.py
tests/test_colored_prints.py
tests/test_colorized_strings.py
tests/test_helpers.py
tests/test_tagged_prints.py
PrintTags-1.5.1.dist-info/LICENSE.md
PrintTags-1.5.1.dist-info/METADATA
PrintTags-1.5.1.dist-info/WHEEL
PrintTags-1.5.1.dist-info/top_level.txt
PrintTags-1.5.1.dist-info/RECORD
